{
    "samples": [
        {
            "ray": [
                -0.36322468519210815,
                -0.4274752736091614
            ],
            "uv": [
                0.07731746395056077,
                0.19226367589837492
            ]
        },
        {
            "ray": [
                -0.22239486873149872,
                -0.4274752736091614
            ],
            "uv": [
                0.21416037232013427,
                0.18966964217593651
            ]
        },
        {
            "ray": [
                -0.08156507462263107,
                -0.4274752736091614
            ],
            "uv": [
                0.3623407339589532,
                0.18995956359197375
            ]
        },
        {
            "ray": [
                0.200094535946846,
                -0.4274752736091614
            ],
            "uv": [
                0.6779736018921187,
                0.2013427939269093
            ]
        },
        {
            "ray": [
                0.34092432260513306,
                -0.4274752736091614
            ],
            "uv": [
                0.8299229419394217,
                0.2098268101014725
            ]
        },
        {
            "ray": [
                -0.36322468519210815,
                -0.2871495485305786
            ],
            "uv": [
                0.057160296025024794,
                0.29413290608072024
            ]
        },
        {
            "ray": [
                -0.22239486873149872,
                -0.2871495485305786
            ],
            "uv": [
                0.19723811703669794,
                0.29709315632867933
            ]
        },
        {
            "ray": [
                -0.08156507462263107,
                -0.2871495485305786
            ],
            "uv": [
                0.3495384145876249,
                0.30293736171511404
            ]
        },
        {
            "ray": [
                0.05926472693681717,
                -0.2871495485305786
            ],
            "uv": [
                0.5114671549553673,
                0.3116807812619211
            ]
        },
        {
            "ray": [
                0.200094535946846,
                -0.2871495485305786
            ],
            "uv": [
                0.6723887998779279,
                0.3238117036697948
            ]
        },
        {
            "ray": [
                0.34092432260513306,
                -0.2871495485305786
            ],
            "uv": [
                0.8298771648737316,
                0.33798733501182576
            ]
        },
        {
            "ray": [
                -0.36322468519210815,
                -0.14682383835315704
            ],
            "uv": [
                0.028976882581826506,
                0.3995727473868925
            ]
        },
        {
            "ray": [
                -0.22239486873149872,
                -0.14682383835315704
            ],
            "uv": [
                0.17042801556420234,
                0.409750514991989
            ]
        },
        {
            "ray": [
                -0.08156507462263107,
                -0.14682383835315704
            ],
            "uv": [
                0.32600900282291906,
                0.42204928664072633
            ]
        },
        {
            "ray": [
                0.05926472693681717,
                -0.14682383835315704
            ],
            "uv": [
                0.49085221637293047,
                0.4371252002746624
            ]
        },
        {
            "ray": [
                0.200094535946846,
                -0.14682383835315704
            ],
            "uv": [
                0.6548104066529336,
                0.45352864881361105
            ]
        },
        {
            "ray": [
                0.34092432260513306,
                -0.14682383835315704
            ],
            "uv": [
                0.81367208361944,
                0.4724193179217212
            ]
        },
        {
            "ray": [
                0.4817541241645813,
                -0.14682383835315704
            ],
            "uv": [
                0.9596246280613413,
                0.4903791866941329
            ]
        },
        {
            "ray": [
                -0.22239486873149872,
                -0.006498115602880716
            ],
            "uv": [
                0.13723964293888763,
                0.5239337758449684
            ]
        },
        {
            "ray": [
                -0.08156507462263107,
                -0.006498115602880716
            ],
            "uv": [
                0.2930647745479515,
                0.5441977569237811
            ]
        },
        {
            "ray": [
                0.05926472693681717,
                -0.006498115602880716
            ],
            "uv": [
                0.4571755550469215,
                0.565972381170367
            ]
        },
        {
            "ray": [
                0.200094535946846,
                -0.006498115602880716
            ],
            "uv": [
                0.6179293507286183,
                0.586831464103151
            ]
        },
        {
            "ray": [
                0.34092432260513306,
                -0.006498115602880716
            ],
            "uv": [
                0.779293507286183,
                0.6089265278095674
            ]
        },
        {
            "ray": [
                0.4817541241645813,
                -0.006498115602880716
            ],
            "uv": [
                0.9274280918593119,
                0.6305180437933928
            ]
        },
        {
            "ray": [
                -0.22239486873149872,
                0.13382761180400848
            ],
            "uv": [
                0.09797817959868772,
                0.6334782940413519
            ]
        },
        {
            "ray": [
                -0.08156507462263107,
                0.13382761180400848
            ],
            "uv": [
                0.2515297169451438,
                0.6614480811779965
            ]
        },
        {
            "ray": [
                0.05926472693681717,
                0.13382761180400848
            ],
            "uv": [
                0.4106813153276875,
                0.6905622949568933
            ]
        },
        {
            "ray": [
                0.200094535946846,
                0.13382761180400848
            ],
            "uv": [
                0.570244907301442,
                0.7170366979476616
            ]
        },
        {
            "ray": [
                0.34092432260513306,
                0.13382761180400848
            ],
            "uv": [
                0.72651255054551,
                0.7427939269092851
            ]
        },
        {
            "ray": [
                0.4817541241645813,
                0.13382761180400848
            ],
            "uv": [
                0.874189364461738,
                0.7670557717250325
            ]
        },
        {
            "ray": [
                -0.22239486873149872,
                0.27415332198143005
            ],
            "uv": [
                0.05838101777676051,
                0.7414206149385825
            ]
        },
        {
            "ray": [
                -0.08156507462263107,
                0.27415332198143005
            ],
            "uv": [
                0.2004425116350042,
                0.7734950789654383
            ]
        },
        {
            "ray": [
                0.05926472693681717,
                0.27415332198143005
            ],
            "uv": [
                0.35558098725871673,
                0.8067750057221332
            ]
        },
        {
            "ray": [
                0.200094535946846,
                0.27415332198143005
            ],
            "uv": [
                0.5111467154955367,
                0.8382848859388113
            ]
        },
        {
            "ray": [
                0.34092432260513306,
                0.27415332198143005
            ],
            "uv": [
                0.6619516289005875,
                0.8675211718928817
            ]
        },
        {
            "ray": [
                0.4817541241645813,
                0.27415332198143005
            ],
            "uv": [
                0.8060120546272984,
                0.8939803158617533
            ]
        },
        {
            "ray": [
                -0.08156507462263107,
                0.4144790470600128
            ],
            "uv": [
                0.14825665674830243,
                0.8735942626077668
            ]
        },
        {
            "ray": [
                0.05926472693681717,
                0.4144790470600128
            ],
            "uv": [
                0.2946822308690013,
                0.9122758831158922
            ]
        },
        {
            "ray": [
                0.200094535946846,
                0.4144790470600128
            ],
            "uv": [
                0.44240482185091934,
                0.948073548485542
            ]
        },
        {
            "ray": [
                0.34092432260513306,
                0.4144790470600128
            ],
            "uv": [
                0.5869077592126345,
                0.9780422674906538
            ]
        },
        {
            "ray": [
                -0.08156507462263107,
                0.554804801940918
            ],
            "uv": [
                0.09901579308766308,
                0.9577172503242543
            ]
        }
    ]
}